{"version":"3.8.0","examples":[{"id":"./spec/a_broken_program_spec.rb[1:1]","description":"raises an error when loaded","full_description":"A broken program raises an error when loaded","status":"passed","file_path":"./spec/a_broken_program_spec.rb","line_number":3,"run_time":0.004202,"pending_message":null},{"id":"./spec/a_working_program_spec.rb[1:1]","description":"not to raise an error when loaded","full_description":"A working program not to raise an error when loaded","status":"passed","file_path":"./spec/a_working_program_spec.rb","line_number":3,"run_time":0.00047,"pending_message":null}],"summary":{"duration":0.010157,"example_count":2,"failure_count":0,"pending_count":0,"errors_outside_of_examples_count":0},"summary_line":"2 examples, 0 failures"}